README.md
setup.py
model_transfer/__init__.py
model_transfer/consts.py
model_transfer/db_formmator.py
model_transfer/draw_formattor.py
model_transfer/filters.py
model_transfer/jorm_formmator.py
model_transfer/main.py
model_transfer/trans_formattor.py
model_transfer/transform.py
model_transfer.egg-info/PKG-INFO
model_transfer.egg-info/SOURCES.txt
model_transfer.egg-info/dependency_links.txt
model_transfer.egg-info/entry_points.txt
model_transfer.egg-info/not-zip-safe
model_transfer.egg-info/requires.txt
model_transfer.egg-info/top_level.txt