Metadata-Version: 1.0
Name: model_transfer
Version: 0.0.5
Summary: Convert Model Lang to All Kinds of model classes
Home-page: https://github.com/ipconfiger
Author: Alexander.Li
Author-email: superpowerlee@gmail.com
License: GPL-3.
Platform: UNKNOWN
